flaskgraph/__init__.py
flaskgraph/graph.py
flaskgraph-0.1.2.dist-info/licenses/LICENSE
flaskgraph-0.1.2.dist-info/METADATA
flaskgraph-0.1.2.dist-info/WHEEL
flaskgraph-0.1.2.dist-info/top_level.txt
flaskgraph-0.1.2.dist-info/RECORD
