Metadata-Version: 2.4
Name: flaskgraph
Version: 0.1.2
Summary: Easily embed Chart.js charts in Flask apps via jinja from the backend
Author-email: dp <davidplajner@hellmann.com>
License: MIT
Keywords: flask,chartjs,charts,visualization,data,graph
Classifier: Programming Language :: Python :: 3
Classifier: Framework :: Flask
Classifier: License :: OSI Approved :: MIT License
License-File: LICENSE
Requires-Dist: MarkupSafe>=2.1
Dynamic: license-file
